adar_api/__init__.py
adar_api/adar.py
adar_api/coap_exceptions.py
adar_api/coap_observer.py
adar_api/coap_pointcloud.py
adar_api/coap_resources.py
adar_api/device_errors.py
adar_api/device_info.py
adar_api/device_status.py
adar_api/duration.py
adar_api/examples/__init__.py
adar_api/examples/foxglove_layout_ADAR.json
adar_api/examples/pointcloud_to_foxglove.py
adar_api/examples/ros/Dockerfile.sonair-adar
adar_api/examples/ros/requirements.txt
adar_api/examples/ros/sonair_adar/.gitignore
adar_api/examples/ros/sonair_adar/README.md
adar_api/examples/ros/sonair_adar/launch/sonair_adar.launch.py
adar_api/examples/ros/sonair_adar/package.xml
adar_api/examples/ros/sonair_adar/resource/sonair_adar
adar_api/examples/ros/sonair_adar/setup.cfg
adar_api/examples/ros/sonair_adar/setup.py
adar_api/examples/ros/sonair_adar/sonair_adar/__init__.py
adar_api/examples/ros/sonair_adar/sonair_adar/point_cloud_ros_publisher.py
adar_api/examples/ros/sonair_adar/start_ros.sh
adar_api/examples/utils.py
adar_api/network_config.py
adar_api/statistics.py
adar_api-1.2.0.dist-info/METADATA
adar_api-1.2.0.dist-info/WHEEL
adar_api-1.2.0.dist-info/entry_points.txt
adar_api-1.2.0.dist-info/licenses/LICENSE
adar_api-1.2.0.dist-info/RECORD
