Metadata-Version: 2.4
Name: adar_api
Version: 1.2.0
Summary: A reference implementation in python that uses the Sonair ADAR CoAP API.
License-Expression: MIT
License-File: LICENSE
Keywords: adar,sonair,ultrasound,adar_api
Requires-Python: >=3.11
Classifier: Programming Language :: Python :: 3
Classifier: Operating System :: OS Independent
Classifier: Intended Audience :: Developers
Classifier: Topic :: Software Development :: Libraries :: Python Modules
Requires-Dist: aiocoap
Requires-Dist: foxglove-sdk
Project-URL: Homepage, https://sonair.com
Project-URL: Source, https://github.com/Sonair-AS/adar_api
